hgc/__init__.py
hgc/samples_frame.py
hgc/constants/__init__.py
hgc/constants/atoms.csv
hgc/constants/constants.py
hgc/constants/ions.csv
hgc/constants/other_than_concentrations.csv
hgc/constants/read_write.py
hgc-0.3.2.dist-info/LICENSE
hgc-0.3.2.dist-info/METADATA
hgc-0.3.2.dist-info/WHEEL
hgc-0.3.2.dist-info/top_level.txt
hgc-0.3.2.dist-info/RECORD
