Metadata-Version: 2.1
Name: hgc
Version: 0.3.2
Summary: A python package for correction, validation and analysis of ground water quality samples
Home-page: https://github.com/KWR-Water/hgc
Author: KWR Water Research Institute
Author-email: martin.korevaar@kwrwater.nl, martin.van.der.schans@kwrwater.nl
License: MIT
Project-URL: Source, https://github.com/KWR-Water/hgc
Project-URL: Documentation, http://hgc.readthedocs.io/en/latest/
Project-URL: Tracker, https://github.com/KWR-Water/hgc/issues
Project-URL: Help, https://github.com/KWR-Water/hgc/issues
Classifier: Development Status :: 4 - Beta
Classifier: Intended Audience :: Science/Research
Classifier: Intended Audience :: Other Audience
Classifier: License :: OSI Approved :: MIT License
Classifier: Programming Language :: Python :: 3.8
Classifier: Programming Language :: Python :: 3.9
Classifier: Programming Language :: Python :: 3.10
Classifier: Programming Language :: Python :: 3.11
Classifier: Topic :: Scientific/Engineering :: Hydrology
Requires-Python: >=3.8
License-File: LICENSE
Requires-Dist: pandas (>=0.23)
Requires-Dist: openpyxl (>=3.0.0)
Requires-Dist: xlrd (>=1.0.0)
Requires-Dist: phreeqpython (>=1.3.2)
Requires-Dist: scipy
